pyppin/__init__.py
pyppin/base/__init__.py
pyppin/base/cache.py
pyppin/base/flex_decorator.py
pyppin/base/import_file.py
pyppin/base/lazyinit.py
pyppin/base/registered_class.py
pyppin/containers/__init__.py
pyppin/containers/iterators.py
pyppin/containers/ring_buffer.py
pyppin/containers/zip_by_key.py
pyppin/file/__init__.py
pyppin/file/dev_null.py
pyppin/file/memfile.py
pyppin/file/tee.py
pyppin/file/types.py
pyppin/iterators/__init__.py
pyppin/iterators/zip_by_key.py
pyppin/math/__init__.py
pyppin/math/functions.py
pyppin/math/histogram.py
pyppin/math/plot_ascii.py
pyppin/os/__init__.py
pyppin/os/bulk_import.py
pyppin/os/list_files.py
pyppin/testing/__init__.py
pyppin/testing/interact.py
pyppin/testing/pprint_object.py
pyppin/testing/trace_on_failure.py
pyppin/testing/turn_taker.py
pyppin/text/__init__.py
pyppin/text/formatter.py
pyppin/text/now_and_then.py
pyppin/text/print_counter.py
pyppin/text/si_prefix.py
pyppin/text/sign.py
pyppin/text/tty.py
pyppin/threading/__init__.py
pyppin/threading/periodic_task.py
pyppin/threading/semaphore.py
pyppin/threading/stack_trace.py
pyppin/threading/stack_trace_internals.py
pyppin/util/__init__.py
pyppin/util/exponential_backoff.py
pyppin/util/expression.py
tests/base/__init__.py
tests/base/cache_test.py
tests/base/flex_decorator_test.py
tests/base/lazyinit_test.py
tests/base/registered_class_test.py
tests/containers/__init__.py
tests/containers/iterators_test.py
tests/containers/ring_buffer_test.py
tests/containers/zip_by_key_test.py
tests/file/__init__.py
tests/file/dev_null_test.py
tests/file/memfile_test.py
tests/file/tee_test.py
tests/iterators/__init__.py
tests/iterators/iterators_test.py
tests/iterators/zip_by_key_test.py
tests/math/__init__.py
tests/math/base_test.py
tests/math/plot_ascii_test.py
tests/os/__init__.py
tests/os/bulk_import_test.py
tests/os/list_files_test.py
tests/os/bulk_import_test_data/__init__.py
tests/os/bulk_import_test_data/_def.py
tests/os/bulk_import_test_data/class1.py
pyppin-1.0.7.dist-info/LICENSE.md
pyppin-1.0.7.dist-info/METADATA
pyppin-1.0.7.dist-info/WHEEL
pyppin-1.0.7.dist-info/top_level.txt
pyppin-1.0.7.dist-info/RECORD
