Metadata-Version: 2.1
Name: pyppin
Version: 1.0.7
Summary: Python tools collection
Author: Yonatan Zunger
Author-email: zunger@gmail.com
License: Apache
Project-URL: Source, https://github.com/yonatanzunger/pyppin
Project-URL: Tracker, https://github.com/yonatanzunger/pyppin/issues
Project-URL: Documentation, https://yonatanzunger.github.io/pyppin/
Keywords: threading,stack trace,utilities
Classifier: Development Status :: 5 - Production/Stable
Classifier: License :: OSI Approved :: Apache Software License
Classifier: Intended Audience :: Developers
Classifier: Programming Language :: Python
Requires-Python: >=3.9
License-File: LICENSE.md
